voicetest/__init__.py
voicetest/api.py
voicetest/cli.py
voicetest/config.py
voicetest/container.py
voicetest/data.py
voicetest/formatting.py
voicetest/llm.py
voicetest/rest.py
voicetest/retry.py
voicetest/runner.py
voicetest/settings.py
voicetest/utils.py
voicetest/demo/__init__.py
voicetest/demo/agent.json
voicetest/demo/tests.json
voicetest/engine/__init__.py
voicetest/engine/agent_gen.py
voicetest/engine/session.py
voicetest/exporters/__init__.py
voicetest/exporters/base.py
voicetest/exporters/bland.py
voicetest/exporters/graph_viz.py
voicetest/exporters/livekit_codegen.py
voicetest/exporters/registry.py
voicetest/exporters/retell_cf.py
voicetest/exporters/retell_llm.py
voicetest/exporters/test_cases.py
voicetest/exporters/vapi.py
voicetest/generic_tests/__init__.py
voicetest/generic_tests/adversarial.py
voicetest/generic_tests/greeting.py
voicetest/generic_tests/hangup.py
voicetest/importers/__init__.py
voicetest/importers/base.py
voicetest/importers/bland.py
voicetest/importers/custom.py
voicetest/importers/livekit.py
voicetest/importers/registry.py
voicetest/importers/retell.py
voicetest/importers/retell_llm.py
voicetest/importers/vapi.py
voicetest/importers/xlsform.py
voicetest/judges/__init__.py
voicetest/judges/flow.py
voicetest/judges/metric.py
voicetest/judges/rule.py
voicetest/models/__init__.py
voicetest/models/agent.py
voicetest/models/results.py
voicetest/models/test_case.py
voicetest/platforms/__init__.py
voicetest/platforms/base.py
voicetest/platforms/bland.py
voicetest/platforms/livekit.py
voicetest/platforms/registry.py
voicetest/platforms/retell.py
voicetest/platforms/vapi.py
voicetest/simulator/__init__.py
voicetest/simulator/user_sim.py
voicetest/storage/__init__.py
voicetest/storage/db.py
voicetest/storage/repositories.py
voicetest/tui/__init__.py
voicetest/tui/app.py
voicetest/tui/shell.py
voicetest/tui/widgets.py
web/dist/favicon-16.svg
web/dist/favicon.svg
web/dist/icon-80.svg
web/dist/index.html
web/dist/logo-dark.svg
voicetest-0.10.dist-info/METADATA
voicetest-0.10.dist-info/WHEEL
voicetest-0.10.dist-info/entry_points.txt
voicetest-0.10.dist-info/licenses/LICENSE
voicetest-0.10.dist-info/RECORD
