Metadata-Version: 2.4
Name: voicetest
Version: 0.10
Summary: A generic test harness for voice agent workflows
Project-URL: Homepage, https://voicetest.dev
Project-URL: Repository, https://github.com/voicetestdev/voicetest
Project-URL: Issues, https://github.com/voicetestdev/voicetest/issues
Author-email: pld <50706+pld@users.noreply.github.com>
License-Expression: Apache-2.0
License-File: LICENSE
Keywords: ai,bland,livekit,retell,testing,vapi,voice
Classifier: Development Status :: 3 - Alpha
Classifier: Intended Audience :: Developers
Classifier: License :: OSI Approved :: Apache Software License
Classifier: Operating System :: OS Independent
Classifier: Programming Language :: Python :: 3
Classifier: Programming Language :: Python :: 3.12
Classifier: Programming Language :: Python :: 3.13
Classifier: Topic :: Software Development :: Testing
Classifier: Typing :: Typed
Requires-Python: >=3.12
Requires-Dist: bland>=0.3.0
Requires-Dist: click>=8.0
Requires-Dist: dspy>=2.6
Requires-Dist: duckdb>=1.4.3
Requires-Dist: fastapi>=0.115
Requires-Dist: livekit-agents<2.0,>=1.0
Requires-Dist: livekit-plugins-openai<2.0,>=1.0
Requires-Dist: livekit-plugins-silero<2.0,>=1.0
Requires-Dist: openpyxl>=3.1.5
Requires-Dist: punq>=0.7.0
Requires-Dist: pyarrow>=22.0.0
Requires-Dist: pydantic>=2.0
Requires-Dist: python-multipart>=0.0.21
Requires-Dist: retell-sdk>=5.0
Requires-Dist: rich>=13.0
Requires-Dist: textual>=7.2.0
Requires-Dist: uvicorn>=0.32
Requires-Dist: vapi-server-sdk>=0.2
Provides-Extra: dev
Requires-Dist: httpx>=0.28; extra == 'dev'
Requires-Dist: pre-commit>=4.0; extra == 'dev'
Requires-Dist: pytest-asyncio>=0.24; extra == 'dev'
Requires-Dist: pytest>=8.0; extra == 'dev'
Requires-Dist: ruff>=0.8; extra == 'dev'
